{"category_type":"topic","category_name":"building","repos_data":[{"full_name":"openremote/openremote","description":"100% open-source IoT Platform - Integrate your devices, create rules, and analyse and visualise your data","topics":["iot-projects","iot-platform","openremote","iot","energy","building","mqtt","websocket","smartcity","dashboard"],"created_at":"2016-02-03T11:14:02Z","pushed_at":"2024-01-12T16:19:01Z","stargazers_count":1002,"language":"Java"}],"frecuent_topics":{"iot-projects":1,"iot-platform":1,"openremote":1,"iot":1,"energy":1}}