{"category_type":"topic","category_name":"calendar","repos_data":[{"full_name":"fullcalendar/fullcalendar","description":"Full-sized drag & drop event calendar in JavaScript","topics":["calendar","event","full-sized"],"created_at":"2009-11-22T23:16:51Z","pushed_at":"2023-12-07T21:35:38Z","stargazers_count":17462,"language":"JavaScript"},{"full_name":"nhn/tui.calendar","description":"🍞📅A JavaScript calendar that has everything you need.","topics":["calendar","fullcalendar","frontend","schedule","javascript","monthly","weekly","daily","task","milestone"],"created_at":"2017-09-11T00:21:04Z","pushed_at":"2024-01-05T00:05:59Z","stargazers_count":11259,"language":"JavaScript"},{"full_name":"amsul/pickadate.js","description":"The mobile-friendly, responsive, and lightweight jQuery date & time input picker.","topics":["picker","date","time","calendar"],"created_at":"2012-11-16T01:36:42Z","pushed_at":"2023-07-14T10:02:54Z","stargazers_count":7701,"language":"CSS"},{"full_name":"IonicaBizau/git-stats","description":"🍀 Local git statistics including GitHub-like contributions calendars.","topics":["contributions-calendar","gitstats","calendar","statistics","hacktoberfest"],"created_at":"2015-02-09T14:06:20Z","pushed_at":"2023-10-20T12:24:29Z","stargazers_count":6280,"language":"JavaScript"},{"full_name":"prolificinteractive/material-calendarview","description":"A Material design back port of Android's CalendarView","topics":["java","material","calendar","android"],"created_at":"2015-02-09T22:31:56Z","pushed_at":"2023-05-28T16:37:44Z","stargazers_count":5897,"language":"Java"},{"full_name":"leits/MeetingBar","description":"🇺🇦 Your meetings at your fingertips in the macOS menu bar ","topics":["swift","calendar","macos","meetings","google-meet","zoom","microsoft-teams","macos-calendar","productivity","apple"],"created_at":"2020-05-07T09:58:08Z","pushed_at":"2024-01-06T23:17:58Z","stargazers_count":4012,"language":"Swift"},{"full_name":"Leantime/leantime","description":"Leantime is a goals focused project management system for non-project managers. Building with ADHD, Autism, and dyslexia in mind.","topics":["project-management","php","sql","kanban","gantt","timesheets","calendar","agile","retrospective","lean"],"created_at":"2015-01-23T17:52:06Z","pushed_at":"2024-01-18T21:00:12Z","stargazers_count":3791,"language":"PHP"},{"full_name":"alamkanak/Android-Week-View","description":"Android Week View is an android library to display calendars (week view or day view) within the app. It supports custom styling.","topics":["android","custom-view","calendar","calendar-view"],"created_at":"2014-09-17T10:07:12Z","pushed_at":"2021-11-20T06:01:14Z","stargazers_count":3404,"language":"Java"},{"full_name":"HowardHinnant/date","description":"A date and time library based on the C++11/14/17 <chrono> header","topics":["date","datetime","timezone","calendar","time","iana-database","timezone-library"],"created_at":"2015-07-18T02:34:13Z","pushed_at":"2024-01-13T10:00:48Z","stargazers_count":2987,"language":"C++"},{"full_name":"bevacqua/rome","description":":calendar: Customizable date (and time) picker. Opt-in UI, no jQuery!","topics":["front-end","javascript","vanilla","calendar","component"],"created_at":"2014-07-18T13:57:29Z","pushed_at":"2022-12-03T02:48:30Z","stargazers_count":2913,"language":"CSS"},{"full_name":"pimutils/khal","description":":calendar: CLI calendar application","topics":["python","calendar","terminal","icalendar"],"created_at":"2013-08-25T11:22:27Z","pushed_at":"2024-01-11T15:36:31Z","stargazers_count":2352,"language":"Python"},{"full_name":"SundeepK/CompactCalendarView","description":"An android library which provides a compact calendar view much like the one used in google calenders.","topics":["calendar","compactcalendarview","android","android-library","android-ui","java","animation"],"created_at":"2015-05-17T17:19:25Z","pushed_at":"2022-05-27T05:53:24Z","stargazers_count":1518,"language":"Java"},{"full_name":"pimutils/vdirsyncer","description":"📇 Synchronize calendars and contacts.","topics":["python","cli","webdav","caldav","carddav","synchronisation","contacts","calendar","tasks","todo"],"created_at":"2014-02-15T15:33:41Z","pushed_at":"2024-01-01T15:57:33Z","stargazers_count":1409,"language":"Makefile"},{"full_name":"espocrm/espocrm","description":"EspoCRM – Open Source CRM Application","topics":["crm","php","single-page-application","customer-portal","calendar","kanban","open-source","platform","sales-automation","customizable"],"created_at":"2014-09-25T13:38:46Z","pushed_at":"2024-01-13T13:35:30Z","stargazers_count":1375,"language":"PHP"},{"full_name":"fightbulc/moment.php","description":"Parse, validate, manipulate, and display dates in PHP w/ i18n support. Inspired by moment.js","topics":["date","time","i18n","internationalization","formatter","moment","php","calendar","parsing"],"created_at":"2012-09-30T20:10:17Z","pushed_at":"2023-08-19T04:09:24Z","stargazers_count":960,"language":"PHP"},{"full_name":"skiff-org/skiff-apps","description":"Privacy-first, end-to-end encrypted Mail, Pages, Drive, and Calendar.","topics":["calendar","collaboration","component-library","cryptography","email","end-to-end-encryption","file-storage","security","typescript","workspace"],"created_at":"2022-04-25T19:28:59Z","pushed_at":"2023-12-05T21:38:48Z","stargazers_count":935,"language":"TypeScript"},{"full_name":"timeoff-management/timeoff-management-application","description":"Simple yet powerful absence management software for small and medium size business (community edition)","topics":["web-app","businessapp","employees","absence","timeoff","calendar","node-js","absence-management","employee-absence","sickness"],"created_at":"2015-11-06T20:15:09Z","pushed_at":"2023-10-29T12:06:55Z","stargazers_count":883,"language":"JavaScript"},{"full_name":"lostdesign/linked","description":"🧾  Daily journaling without distraction. An easy, distraction-free way to record your thoughts, declutter your mind and keep the things you want to remember. Join the discord at https://discord.gg/uNjJzZvccr","topics":["electron","vue","thoughts","journal","calendar","sponsor","yarn","notes","note-taking","daily"],"created_at":"2021-03-18T17:40:15Z","pushed_at":"2023-10-26T00:13:26Z","stargazers_count":805,"language":"JavaScript"},{"full_name":"itflow-org/itflow","description":"Free and open-source web application for MSPs that streamlines IT documentation, ticketing, invoicing, and accounting, an alternative to ITGlue. It helps in managing and organizing client's IT information, increasing efficiency and profitability.","topics":["crm","ticketing-system","ticket-management","accounting","managed-services","asset-management","mileage","calendar","documentation","invoicing"],"created_at":"2019-03-13T17:47:57Z","pushed_at":"2024-01-12T23:41:37Z","stargazers_count":422,"language":"PHP"},{"full_name":"thamara/time-to-leave","description":"Log work hours and get notified when it's time to leave the office and start to live.","topics":["electron","electron-app","js","calendar","time-tracker","working-hours","productivity","eletronic-timecard","timecard","office"],"created_at":"2019-09-13T22:57:09Z","pushed_at":"2024-01-13T16:35:45Z","stargazers_count":421,"language":"CSS"},{"full_name":"progmaticltd/homebox","description":"A set of ansible scripts to build a personal mail server / private cloud / etc.","topics":["ansible-scripts","dkim","self-hosted","sogo","sieve","rspamd","calendar","embedded-dns-server","sshfp","dnssec"],"created_at":"2017-03-12T20:32:20Z","pushed_at":"2024-01-12T07:37:16Z","stargazers_count":416,"language":"Shell"},{"full_name":"MenoData/Time4J","description":"Advanced date, time and interval library for Java with sun/moon-astronomy and calendars like Chinese, Coptic, Ethiopian, French Republican, Hebrew, Hijri, Historic Christian, Indian National, Japanese, Julian, Korean, Minguo, Persian, Thai, Vietnamese","topics":["java","time4j","calendar","interval","duration","sun","moon","timezone"],"created_at":"2013-07-25T04:50:05Z","pushed_at":"2024-01-08T15:32:17Z","stargazers_count":408,"language":"Java"},{"full_name":"ekreutz/CornerCal","description":"A simple, clean calendar and clock app for macOS.","topics":["macos","clock","calendar","calendar-widget","macosx","corner-cal","ui","ui-design"],"created_at":"2017-10-15T06:08:49Z","pushed_at":"2020-05-03T07:07:26Z","stargazers_count":236,"language":"Swift"},{"full_name":"EGroupware/egroupware","description":"Web based groupware server written in PHP, forum at https://help.egroupware.org/","topics":["egroupware","webmail","project-management","address-book","calendar","caldav-server","carddav-server","php","javascript","collaboration"],"created_at":"2016-05-12T11:53:59Z","pushed_at":"2024-01-13T12:56:38Z","stargazers_count":228,"language":"JavaScript"},{"full_name":"Intermesh/groupoffice","description":"Group Office groupware and CRM","topics":["groupware","crm","collaboration","email","calendar","address-book","file-sharing"],"created_at":"2018-03-08T14:50:33Z","pushed_at":"2024-01-12T16:10:44Z","stargazers_count":156,"language":"Shell"},{"full_name":"intri-in/manage-my-damn-life-nextjs","description":"Manage My Damn Life (MMDL) is a self-hosted front end for managing your CalDAV tasks and calendars.","topics":["caldav","caldav-client","calendar","task-manager","taskmanager","tasks","calendar-view","self-hosted","selfhosted"],"created_at":"2023-04-11T16:59:52Z","pushed_at":"2023-12-26T13:41:38Z","stargazers_count":84,"language":"JavaScript"},{"full_name":"nathan-osman/go-sunrise","description":"Go package for calculating the sunrise and sunset times for a given location","topics":["golang","calendar","astronomy","sunrise","sunset"],"created_at":"2017-06-15T20:49:41Z","pushed_at":"2023-04-28T16:23:26Z","stargazers_count":79,"language":"Go"},{"full_name":"anoopt/ms-graph-create-event","description":":calendar: A GitHub action to create Outlook calendar event using Microsoft Graph","topics":["github-actions","actions","microsoft-graph","calendar"],"created_at":"2019-12-02T01:06:57Z","pushed_at":"2022-12-10T10:46:36Z","stargazers_count":9,"language":"JavaScript"}],"frecuent_topics":{"calendar":28,"php":4,"javascript":3,"date":3,"time":3}}