{"category_type":"topic","category_name":"cancel","repos_data":[{"full_name":"vardius/gollback","description":"Go asynchronous simple function utilities, for managing execution of closures and callbacks","topics":["goroutine","callback","closure","golang","retry","race","cancel","timeout","promise","future"],"created_at":"2019-05-11T05:56:37Z","pushed_at":"2023-02-16T21:51:46Z","stargazers_count":116,"language":"Go"}],"frecuent_topics":{"goroutine":1,"callback":1,"closure":1,"golang":1,"retry":1}}