{"category_type":"topic","category_name":"cgo","repos_data":[{"full_name":"sbinet/go-python","description":"naive go bindings to the CPython2 C-API","topics":["python2","go","golang","cgo"],"created_at":"2012-07-09T15:43:31Z","pushed_at":"2023-07-24T07:11:30Z","stargazers_count":1516,"language":"Makefile"},{"full_name":"crazy-max/ghaction-xgo","description":"GitHub Action for xgo, a Golang CGO cross compiler","topics":["github-actions","golang","cgo","cross-compiler","actions","xgo"],"created_at":"2019-09-15T21:42:18Z","pushed_at":"2023-12-18T12:04:23Z","stargazers_count":61,"language":"Go"},{"full_name":"songtianyi/go-mxnet-predictor","description":" go binding for mxnet c_predict_api to do inference with pre-trained model","topics":["machine-learning","mxnet","golang","cgo","inference","deep-learning"],"created_at":"2016-12-12T10:28:04Z","pushed_at":"2018-06-06T11:41:16Z","stargazers_count":55,"language":"Go"},{"full_name":"prashantgupta24/mac-sleep-notifier","description":"macOS Sleep/ Wake notifications in golang","topics":["macos","sleep","cgo","golang","c"],"created_at":"2019-03-30T00:43:23Z","pushed_at":"2019-06-17T15:59:38Z","stargazers_count":30,"language":"Makefile"}],"frecuent_topics":{"golang":4,"cgo":4,"python2":1,"go":1,"github-actions":1}}