{"category_type":"topic","category_name":"color-themes","repos_data":[{"full_name":"CodingFriends/Tincta","description":"Tincta is a one-window text editor for macOS with focus on speed, stability and ease of use.","topics":["text","editor","syntax-highlighting","macos","regex-support","color-themes","mac","app","code"],"created_at":"2016-09-05T16:21:21Z","pushed_at":"2022-10-24T09:05:19Z","stargazers_count":144,"language":"Objective-C"}],"frecuent_topics":{"text":1,"editor":1,"syntax-highlighting":1,"macos":1,"regex-support":1}}