{"category_type":"topic","category_name":"cooperative","repos_data":[{"full_name":"foodcoops/foodsoft","description":"Web-based software to manage a non-profit food coop (product catalog, ordering, accounting, job scheduling).","topics":["food-cooperative","foodcoop","food","cooperative","product-catalog","membership","foodsoft"],"created_at":"2009-01-07T22:38:49Z","pushed_at":"2023-12-22T14:36:23Z","stargazers_count":304,"language":"Ruby"}],"frecuent_topics":{"food-cooperative":1,"foodcoop":1,"food":1,"cooperative":1,"product-catalog":1}}