{"category_type":"topic","category_name":"copying","repos_data":[{"full_name":"xtyrrell/undollar","description":"undollar eats the dollar sign in the command you just pasted into your terminal","topics":["command-line","convenience","copy-paste","shameless","stackoverflow","copying"],"created_at":"2017-12-24T12:51:32Z","pushed_at":"2018-09-14T19:07:56Z","stargazers_count":156,"language":"JavaScript"}],"frecuent_topics":{"command-line":1,"convenience":1,"copy-paste":1,"shameless":1,"stackoverflow":1}}