{"category_type":"topic","category_name":"emitter","repos_data":[{"full_name":"emitter-io/emitter","description":"High performance, distributed and low latency publish-subscribe platform.","topics":["pubsub","networking","emitter","mqtt","mqtt-broker","realtime","high-performance","low-latency","golang","go"],"created_at":"2016-10-29T08:52:21Z","pushed_at":"2023-12-18T19:41:56Z","stargazers_count":3683,"language":"Go"},{"full_name":"olebedev/emitter","description":"Emits events in Go way, with wildcard, predicates, cancellation possibilities and many other good wins","topics":["emitter","golang"],"created_at":"2015-11-10T20:56:36Z","pushed_at":"2023-04-11T05:06:14Z","stargazers_count":489,"language":"Go"},{"full_name":"biojppm/rapidyaml","description":"Rapid YAML - a library to parse and emit YAML, and do it fast.","topics":["yaml","json","parser","emitter","serialization","rapid","custom-allocator","stl","cplusplus","cpp11"],"created_at":"2018-01-04T18:54:22Z","pushed_at":"2024-01-11T21:08:35Z","stargazers_count":488,"language":"CMake"}],"frecuent_topics":{"emitter":3,"golang":2,"pubsub":1,"networking":1,"mqtt":1}}