{"category_type":"topic","category_name":"explainable-ml","repos_data":[{"full_name":"MAIF/shapash","description":"🔅 Shapash: User-friendly Explainability and Interpretability to Develop Reliable and Transparent Machine Learning Models","topics":["python","machine-learning","explainability","explainable-ml","transparency","ethical-artificial-intelligence","shap","lime","interpretability"],"created_at":"2020-04-29T07:34:23Z","pushed_at":"2024-01-11T17:20:15Z","stargazers_count":2549,"language":"Makefile"},{"full_name":"AstraZeneca/awesome-explainable-graph-reasoning","description":"A collection of research papers and software related to explainability in graph machine learning.","topics":["awesome-list","graph","graph-algorithms","deep-learning","explainable-ai","explainable-ml","graphml"],"created_at":"2021-06-07T09:23:43Z","pushed_at":"2022-04-04T14:54:08Z","stargazers_count":1929,"language":null},{"full_name":"benedekrozemberczki/shapley","description":"The official implementation of \"The Shapley Value of Classifiers in Ensemble Games\" (CIKM 2021).","topics":["shapley","shapley-value","owen","voting-classifier","machine-learning","classifier","random-forest","random-forest-classifier","explainable-ml","explainable-ai"],"created_at":"2020-01-30T14:06:40Z","pushed_at":"2023-07-01T21:42:58Z","stargazers_count":205,"language":"Python"}],"frecuent_topics":{"explainable-ml":3,"machine-learning":2,"explainable-ai":2,"python":1,"explainability":1}}