{"category_type":"topic","category_name":"filesystem-library","repos_data":[{"full_name":"thephpleague/flysystem","description":"Abstraction for local and remote filesystems","topics":["filesystem","php","thephpleague","filesystem-library"],"created_at":"2013-10-27T11:07:22Z","pushed_at":"2024-01-12T09:25:47Z","stargazers_count":13103,"language":"PHP"},{"full_name":"PyFilesystem/pyfilesystem2","description":"Python's Filesystem abstraction layer","topics":["filesystem","pyfilesystem","pyfilesystem2","python","ftp","tar","zip","filesystem-library"],"created_at":"2016-10-14T15:05:27Z","pushed_at":"2023-11-06T03:24:02Z","stargazers_count":1921,"language":"Python"},{"full_name":"rjeczalik/notify","description":"File system event notification library on steroids.","topics":["golang","filesystem-library","notifications","filesystem-events"],"created_at":"2014-09-08T16:09:34Z","pushed_at":"2023-10-31T15:29:01Z","stargazers_count":868,"language":"Go"}],"frecuent_topics":{"filesystem-library":3,"filesystem":2,"php":1,"thephpleague":1,"pyfilesystem":1}}