{"category_type":"topic","category_name":"flask-monitoring-dashboard","repos_data":[{"full_name":"flask-dashboard/Flask-MonitoringDashboard","description":"Automatically monitor the evolving performance of Flask/Python web services.","topics":["flask","dashboard","flask-monitoring-dashboard","flask-extension","python","monitoring","profiler"],"created_at":"2017-04-11T13:50:14Z","pushed_at":"2023-12-16T15:49:58Z","stargazers_count":723,"language":"Python"}],"frecuent_topics":{"flask":1,"dashboard":1,"flask-monitoring-dashboard":1,"flask-extension":1,"python":1}}