{"category_type":"topic","category_name":"harfang-3d-framework","repos_data":[{"full_name":"harfang3d/harfang-go","description":"HARFANG 3D engine for the Go language","topics":["bgfx-graphics-library","directx","go","golang","harfang-3d-framework","harfang3d","opengl","opengl-es","physics","vulkan"],"created_at":"2022-06-16T07:22:00Z","pushed_at":"2022-12-13T15:34:36Z","stargazers_count":37,"language":"Go"}],"frecuent_topics":{"bgfx-graphics-library":1,"directx":1,"go":1,"golang":1,"harfang-3d-framework":1}}