{"category_type":"topic","category_name":"hub","repos_data":[{"full_name":"ultralytics/ultralytics","description":"NEW - YOLOv8 🚀 in PyTorch > ONNX > OpenVINO > CoreML > TFLite","topics":["hub","ultralytics","yolov8","yolov5","yolo","yolov3","deep-learning","image-classification","machine-learning","object-detection"],"created_at":"2022-09-11T16:39:45Z","pushed_at":"2024-01-08T15:09:11Z","stargazers_count":17936,"language":"Python"},{"full_name":"aerokube/selenoid","description":"Selenium Hub successor running browsers within containers. Scalable, immutable, self hosted Selenium-Grid on any platform with single binary.","topics":["selenium","hub","docker","vnc","selenium-server","grid","selenium-grid","selenium-webdriver"],"created_at":"2016-08-22T09:11:16Z","pushed_at":"2024-01-09T08:39:46Z","stargazers_count":2441,"language":"Go"}],"frecuent_topics":{"hub":2,"ultralytics":1,"yolov8":1,"yolov5":1,"yolo":1}}