{"category_type":"topic","category_name":"igraph","repos_data":[{"full_name":"benedekrozemberczki/awesome-community-detection","description":"A curated list of community detection research papers with implementations. ","topics":["graph-clustering","network-clustering","clustering","dimensionality-reduction","factorization","embedding","deep-learning","matrix-factorization","igraph","networkx"],"created_at":"2018-10-10T15:17:30Z","pushed_at":"2023-12-27T07:48:24Z","stargazers_count":2233,"language":"Python"}],"frecuent_topics":{"graph-clustering":1,"network-clustering":1,"clustering":1,"dimensionality-reduction":1,"factorization":1}}