{"category_type":"topic","category_name":"image-cropper","repos_data":[{"full_name":"fengyuanchen/cropper","description":"⚠️ [Deprecated] No longer maintained, please use https://github.com/fengyuanchen/jquery-cropper","topics":["image-cropper","image-processing","cropper","jquery","jquery-plugin"],"created_at":"2014-02-19T07:48:10Z","pushed_at":"2020-07-21T10:46:15Z","stargazers_count":7771,"language":"CSS"}],"frecuent_topics":{"image-cropper":1,"image-processing":1,"cropper":1,"jquery":1,"jquery-plugin":1}}