{"category_type":"topic","category_name":"jetty","repos_data":[{"full_name":"dropwizard/dropwizard","description":"A damn simple library for building production-ready RESTful web services.","topics":["dropwizard","java","web-framework","rest","hibernate","jersey2","jetty","jax-rs","jdbi","jersey-framework"],"created_at":"2011-01-19T19:52:29Z","pushed_at":"2024-01-13T13:13:19Z","stargazers_count":8434,"language":"Shell"}],"frecuent_topics":{"dropwizard":1,"java":1,"web-framework":1,"rest":1,"hibernate":1}}