{"category_type":"topic","category_name":"latex","repos_data":[{"full_name":"JabRef/jabref","description":"Graphical Java application for managing BibTeX and biblatex (.bib) databases","topics":["jabref","bibtex","java","latex","biblatex","bibliography","academia","reference-manager","research-tool","academic-publications"],"created_at":"2014-03-11T14:48:42Z","pushed_at":"2024-01-13T16:32:19Z","stargazers_count":3249,"language":"Python"},{"full_name":"xiaohanyu/awesome-tikz","description":"A curated list of awesome TikZ documentations, libraries and resources","topics":["awesome","awesome-list","tikz","latex","tex"],"created_at":"2017-02-11T09:31:03Z","pushed_at":"2021-04-04T10:11:28Z","stargazers_count":1370,"language":"unknown"},{"full_name":"xu-cheng/latex-action","description":":octocat: GitHub Action to compile LaTeX documents","topics":["github-actions","latex"],"created_at":"2019-08-21T07:43:22Z","pushed_at":"2023-10-09T22:14:13Z","stargazers_count":971,"language":"Shell"},{"full_name":"qilin-editor/qilin-app","description":"Fully hackable text editor developed for exact sciences with built-in KaTeX and AsciiMath support. Extensible via plugins and themes. Exportable as HTML, PDF and GFM.","topics":["latex","katex","asciimath","editor","physics","mathematics","macos","windows","linux","nwjs"],"created_at":"2016-09-01T21:28:25Z","pushed_at":"2020-12-07T02:06:45Z","stargazers_count":425,"language":"HTML"},{"full_name":"Linbreux/wikmd","description":"A file based wiki that uses markdown","topics":["wiki","latex","pandoc","markdown","markdown-viewer","html","docker","selfhost","markdown-to-html","markdown-editor"],"created_at":"2020-11-24T13:54:03Z","pushed_at":"2023-12-30T18:19:48Z","stargazers_count":265,"language":"HTML"},{"full_name":"melmothx/amusewiki","description":"Text::Amuse-based publishing platform","topics":["perl","wiki","wiki-engine","latex","cms","blog-engine","publishing","epub","opds","catalyst"],"created_at":"2014-03-01T16:36:09Z","pushed_at":"2024-01-13T17:08:25Z","stargazers_count":154,"language":"Perl"}],"frecuent_topics":{"latex":6,"wiki":2,"jabref":1,"bibtex":1,"java":1}}