{"category_type":"topic","category_name":"lightning-network","repos_data":[{"full_name":"btcpayserver/btcpayserver","description":"Accept Bitcoin payments. Free, open-source & self-hosted, Bitcoin payment processor. ","topics":["bitcoin","bitcoin-payment-gateway","lightning-network","payment-gateway","bitcoin-payment-processor","crowdfunding","point-of-sale","selfhosted"],"created_at":"2017-08-18T12:57:05Z","pushed_at":"2024-01-20T14:55:26Z","stargazers_count":5632,"language":"C#"},{"full_name":"alexk111/awesome-bitcoin-payment-processors","description":"🌟 A curated list of Bitcoin payment processors enabling merchants, businesses and nonprofits to accept Bitcoin payments.","topics":["awesome-lists","bitcoin","payment-processing","awesome-list","awesome","bitcoin-payment","payment-processors","lightning","lightning-network","btc"],"created_at":"2018-12-26T03:24:40Z","pushed_at":"2024-01-05T12:16:10Z","stargazers_count":367,"language":"unknown"}],"frecuent_topics":{"bitcoin":2,"lightning-network":2,"bitcoin-payment-gateway":1,"payment-gateway":1,"bitcoin-payment-processor":1}}