{"category_type":"topic","category_name":"manuals","repos_data":[{"full_name":"trimstray/the-book-of-secret-knowledge","description":"A collection of inspiring lists, manuals, cheatsheets, blogs, hacks, one-liners, cli/web tools and more.","topics":["awesome","awesome-list","lists","manuals","resources","howtos","hacks","search-engines","one-liners","cheatsheets"],"created_at":"2018-06-23T10:43:14Z","pushed_at":"2024-01-06T23:48:54Z","stargazers_count":118340,"language":"unknown"},{"full_name":"typemill/typemill","description":"Typemill is a lightweight, flat-file CMS designed for simple, fast, and flexible website and eBook creation using Markdown.","topics":["manuals","docs","documentation","cms-framework","ebooks","markdown-editor","php8","publication","self-hosted","slim4"],"created_at":"2017-04-12T21:01:11Z","pushed_at":"2023-12-27T11:37:12Z","stargazers_count":414,"language":"PHP"}],"frecuent_topics":{"manuals":2,"awesome":1,"awesome-list":1,"lists":1,"resources":1}}