{"category_type":"topic","category_name":"model-registry","repos_data":[{"full_name":"iterative/mlem","description":"🐶 A tool to package, serve, and deploy any ML model on any platform. Archived to be resurrected one day🤞","topics":["python","data-science","machine-learning","developer-tools","model-registry","deployment","git","mlem","cli"],"created_at":"2021-09-30T08:07:34Z","pushed_at":"2023-09-13T18:27:00Z","stargazers_count":709,"language":"Python"}],"frecuent_topics":{"python":1,"data-science":1,"machine-learning":1,"developer-tools":1,"model-registry":1}}