{"category_type":"topic","category_name":"neural-nets","repos_data":[{"full_name":"deeplearning4j/deeplearning4j","description":"Suite of tools for deploying and training deep learning models using the JVM. Highlights include model import for keras, tensorflow, and onnx/pytorch, a modular and tiny c++ library for running math code and a java based math library on top of the core c++ library. Also includes samediff: a pytorch/tensorflow like library for running deep learning using automatic differentiation.","topics":["java","gpu","deeplearning","neural-nets","deeplearning4j","dl4j","hadoop","spark","intellij","artificial-intelligence"],"created_at":"2013-11-27T02:03:28Z","pushed_at":"2023-12-22T07:28:11Z","stargazers_count":13293,"language":"Java"},{"full_name":"Atcold/NYU-DLSP20","description":"NYU Deep Learning Spring 2020","topics":["jupyter-notebook","pytorch","deep-learning","neural-nets"],"created_at":"2018-07-09T11:40:25Z","pushed_at":"2023-12-29T19:26:06Z","stargazers_count":6595,"language":"Jupyter Notebook"},{"full_name":"jolibrain/deepdetect","description":"Deep Learning API and Server in C++14 support for Caffe, PyTorch,TensorRT, Dlib, NCNN, Tensorflow, XGBoost and TSNE","topics":["deep-learning","machine-learning","caffe","xgboost","rest-api","tsne","object-detection","image-segmentation","image-classification","neural-nets"],"created_at":"2015-05-22T14:45:28Z","pushed_at":"2024-01-10T10:48:04Z","stargazers_count":2491,"language":"CMake"}],"frecuent_topics":{"neural-nets":3,"deep-learning":2,"java":1,"gpu":1,"deeplearning":1}}