{"category_type":"topic","category_name":"numerical-derivation","repos_data":[{"full_name":"autodiff/autodiff","description":"automatic differentiation made easier for C++","topics":["automatic-differentiation","auto-differentiation","autodiff","autodifferentiation","differentiation","derivatives","numerical-derivation"],"created_at":"2018-07-19T07:28:38Z","pushed_at":"2024-01-13T11:06:50Z","stargazers_count":1454,"language":"CMake"}],"frecuent_topics":{"automatic-differentiation":1,"auto-differentiation":1,"autodiff":1,"autodifferentiation":1,"differentiation":1}}