{"category_type":"topic","category_name":"projections","repos_data":[{"full_name":"SciTools/cartopy","description":"Cartopy - a cartographic python library with matplotlib support","topics":["cartopy","matplotlib","python","geometry","maps","spatial","projections"],"created_at":"2012-08-03T07:43:59Z","pushed_at":"2024-01-12T10:10:54Z","stargazers_count":1318,"language":"Python"},{"full_name":"BitTacklr/Projac","description":"A set of .NET projection libraries","topics":["event-sourcing","c-sharp","sql","projections"],"created_at":"2013-03-23T10:21:01Z","pushed_at":"2022-12-07T18:37:26Z","stargazers_count":138,"language":"C#"}],"frecuent_topics":{"projections":2,"cartopy":1,"matplotlib":1,"python":1,"geometry":1}}