{"category_type":"topic","category_name":"prototyping","repos_data":[{"full_name":"penpot/penpot","description":"Penpot - The Open-Source design & prototyping platform","topics":["ux-design","ux-experience","prototyping","clojure","clojurescript","ui","design"],"created_at":"2015-12-29T22:09:07Z","pushed_at":"2024-01-13T13:07:51Z","stargazers_count":25274,"language":"Clojure"},{"full_name":"evolus/pencil","description":"The Pencil Project's unique mission is to build a free and opensource tool for making diagrams and GUI prototyping that everyone can use. ","topics":["pencil","nodejs","electron","sketching","ui-design","prototyping","javascript","mockup","drawing","wireframe"],"created_at":"2014-06-19T06:23:06Z","pushed_at":"2023-12-15T08:30:50Z","stargazers_count":8858,"language":"JavaScript"},{"full_name":"Raathigesh/atmo","description":":heavy_check_mark: Mock data for your prototypes and demos. Remote deployments to Zeit now.","topics":["atmo","prototyping","mock-services","mock-server","zeit"],"created_at":"2016-05-22T08:13:16Z","pushed_at":"2021-05-31T08:46:08Z","stargazers_count":816,"language":"JavaScript"}],"frecuent_topics":{"prototyping":3,"ux-design":1,"ux-experience":1,"clojure":1,"clojurescript":1}}