{"category_type":"topic","category_name":"python-script","repos_data":[{"full_name":"sivel/speedtest-cli","description":"Command line interface for testing internet bandwidth using speedtest.net","topics":["python","python-library","python-script","speedtest"],"created_at":"2012-09-10T19:17:53Z","pushed_at":"2023-12-04T15:55:39Z","stargazers_count":13127,"language":"Python"},{"full_name":"dashingsoft/pyarmor","description":"A tool used to obfuscate python scripts, bind obfuscated scripts to fixed machine or expire obfuscated scripts.","topics":["python","obfuscation","obfuscate","python-script","obfuscate-scripts"],"created_at":"2017-08-26T04:11:53Z","pushed_at":"2023-12-31T03:46:08Z","stargazers_count":2690,"language":"Python"},{"full_name":"mitre/multiscanner","description":"Modular file scanning/analysis framework","topics":["python","analytic-machines","analysis-framework","python-script","linux","scanning","antivirus","metadata","yara","malware"],"created_at":"2015-04-13T14:58:48Z","pushed_at":"2019-10-08T14:12:14Z","stargazers_count":603,"language":"Python"}],"frecuent_topics":{"python":3,"python-script":3,"python-library":1,"speedtest":1,"obfuscation":1}}