{"category_type":"topic","category_name":"restful","repos_data":[{"full_name":"apache/dubbo","description":"The java implementation of Apache Dubbo. An RPC and microservice framework.","topics":["dubbo","distributed-systems","framework","java","microservices","restful","rpc","grpc","http","service-mesh"],"created_at":"2012-06-19T07:56:02Z","pushed_at":"2024-01-13T10:17:04Z","stargazers_count":39740,"language":"Java"},{"full_name":"nicolargo/glances","description":"Glances an Eye on your system. A top/htop alternative for GNU/Linux, BSD, Mac OS and Windows operating systems.","topics":["python","multi-platform","monitoring","system","terminal","web","restful","restful-api"],"created_at":"2011-12-04T08:49:15Z","pushed_at":"2024-01-07T17:52:28Z","stargazers_count":24152,"language":"Python"},{"full_name":"playframework/playframework","description":"The Community Maintained High Velocity Web Framework For Java and Scala.","topics":["scala","java","reactive","web-framework","restful","play","playframework","jvm","framework","webapps"],"created_at":"2011-09-07T09:24:08Z","pushed_at":"2024-01-13T03:22:34Z","stargazers_count":12474,"language":"Scala"},{"full_name":"lets-blade/blade","description":":rocket: Lightning fast and elegant mvc framework for Java8","topics":["mvc-framework","restful","blade","netty4","template-engine","java8"],"created_at":"2015-06-10T03:35:49Z","pushed_at":"2023-11-28T05:47:52Z","stargazers_count":5812,"language":"Java"},{"full_name":"noirbizarre/flask-restplus","description":"Fully featured framework for fast, easy and documented API development with Flask","topics":["python","api","swagger","flask","rest","json","restful","restplus"],"created_at":"2014-08-14T13:26:03Z","pushed_at":"2023-03-22T17:28:05Z","stargazers_count":2722,"language":"Python"},{"full_name":"Corvusoft/restbed","description":"Corvusoft's Restbed framework brings asynchronous RESTful functionality to C++14 applications.","topics":["restful","restful-webservices","restful-api","cpp","async-programming","asynchronous","http","http-server","http2","websocket"],"created_at":"2015-06-19T15:07:39Z","pushed_at":"2023-04-20T01:38:43Z","stargazers_count":1877,"language":"CMake"},{"full_name":"zalando/nakadi","description":"A distributed event bus that implements a RESTful API abstraction on top of Kafka-like queues","topics":["java","apis","event-bus","restful","microservices","postgresql","kafka","java-8","data-infrastructure"],"created_at":"2015-10-14T08:30:17Z","pushed_at":"2023-12-20T09:57:31Z","stargazers_count":928,"language":"Shell"},{"full_name":"diogo-fernan/malsub","description":"A Python RESTful API framework for online malware analysis and threat intelligence services.","topics":["python","cybersecurity","malware","malware-analysis","api-client","restful","virustotal","restful-client"],"created_at":"2015-02-27T22:43:24Z","pushed_at":"2023-06-20T05:38:07Z","stargazers_count":360,"language":"Python"},{"full_name":"charlesabarnes/SPFtoolbox","description":"SPFtoolbox is a Javascript and PHP app to look up DNS records such as SPF, MX, Whois, and more","topics":["spf","dns-record","domain","lookup","php","javascript","restful","rest-api","mxtoolbox","mxtoolbox-alternative"],"created_at":"2017-07-19T19:29:31Z","pushed_at":"2024-01-08T07:04:40Z","stargazers_count":250,"language":"PHP"},{"full_name":"alioygur/gores","description":"Go package that handles HTML, JSON, XML and etc. responses","topics":["go","golang","restful","rest-api","json-serialization","json-api","http-response"],"created_at":"2015-12-25T12:41:01Z","pushed_at":"2021-01-01T12:48:26Z","stargazers_count":102,"language":"Go"},{"full_name":"cyruzin/tome","description":"Package tome was designed to paginate simple RESTful APIs.","topics":["go","golang","pagination","api","rest","restful"],"created_at":"2019-04-12T16:49:45Z","pushed_at":"2022-04-20T16:41:33Z","stargazers_count":35,"language":"Go"}],"frecuent_topics":{"restful":11,"java":3,"python":3,"framework":2,"microservices":2}}