{"category_type":"topic","category_name":"statuspage","repos_data":[{"full_name":"cstate/cstate","description":"🔥 Open source static (serverless) status page. Uses hyperfast Go & Hugo, minimal HTML/CSS/JS, customizable, outstanding browser support (IE8+), preloaded CMS, read-only API, badges & more.","topics":["hugo","netlify","status","statuspage","fast","light","ie8","ie10","ie11","github-pages"],"created_at":"2017-04-13T13:18:59Z","pushed_at":"2024-01-05T15:05:24Z","stargazers_count":2264,"language":"HTML"},{"full_name":"valeriansaliou/vigil","description":"🚦 Microservices Status Page. Monitors a distributed infrastructure and sends alerts (Slack, SMS, etc.).","topics":["microservices","infrastructure","monitor","slack","status","statuspage","servers","monitoring","infrastructure-services","vigil"],"created_at":"2018-01-10T18:15:39Z","pushed_at":"2023-10-13T18:20:02Z","stargazers_count":1573,"language":"Rust"},{"full_name":"ks888/LambStatus","description":"[Maintenance mode] Serverless Status Page System","topics":["serverless","aws-lambda","statuspage","react","redux","nodejs","javascript","cloudformation","lambda"],"created_at":"2016-08-24T15:00:54Z","pushed_at":"2020-03-25T13:27:14Z","stargazers_count":1305,"language":"JavaScript"},{"full_name":"crazy-max/ghaction-github-status","description":"GitHub Action to check GitHub Status in your workflow","topics":["github-actions","github","statuspage","status","monitoring"],"created_at":"2020-05-22T21:59:38Z","pushed_at":"2023-10-17T23:29:36Z","stargazers_count":32,"language":"TypeScript"}],"frecuent_topics":{"statuspage":4,"status":3,"monitoring":2,"hugo":1,"netlify":1}}