{"category_type":"topic","category_name":"swr","repos_data":[{"full_name":"vercel/swr","description":"React Hooks for Data Fetching","topics":["react","hook","data-fetching","swr","suspense","react-native","fetch","vercel","stale-while-revalidate","hooks"],"created_at":"2019-10-28T18:16:01Z","pushed_at":"2024-01-01T21:50:49Z","stargazers_count":28686,"language":"JavaScript"},{"full_name":"Kong/swrv","description":"Stale-while-revalidate data fetching for Vue","topics":["vue","swr"],"created_at":"2020-01-25T20:58:37Z","pushed_at":"2023-07-27T21:30:53Z","stargazers_count":2043,"language":"JavaScript"}],"frecuent_topics":{"swr":2,"react":1,"hook":1,"data-fetching":1,"suspense":1}}