{"category_type":"topic","category_name":"time-keeping","repos_data":[{"full_name":"kromitgmbh/titra","description":"titra - modern open source project time tracking for freelancers and small teams","topics":["open-source","meteorjs","javascript","node-js","docker","wekan","mongodb-database","time-keeping","time-tracking"],"created_at":"2016-12-19T10:55:48Z","pushed_at":"2024-01-10T09:06:32Z","stargazers_count":370,"language":"HTML"}],"frecuent_topics":{"open-source":1,"meteorjs":1,"javascript":1,"node-js":1,"docker":1}}