{"category_type":"topic","category_name":"visual-regression","repos_data":[{"full_name":"mojoaxel/awesome-regression-testing","description":"🕶️ A curated list of resources around the topic: visual regression testing","topics":["awesome-list","awesome","visual-regression","regression-tests","selenium","phantomcss","phantomjs","hacktoberfest"],"created_at":"2017-06-28T07:50:54Z","pushed_at":"2023-11-20T16:08:05Z","stargazers_count":2039,"language":"unknown"}],"frecuent_topics":{"awesome-list":1,"awesome":1,"visual-regression":1,"regression-tests":1,"selenium":1}}