{"category_type":"topic","category_name":"web-service","repos_data":[{"full_name":"philippgille/ln-paywall","description":"Go middleware for monetizing your API on a per-request basis with Bitcoin and Lightning ⚡️","topics":["go","golang","middleware","micropayments","pay-per-call","api","bitcoin","lightning","paywall","web-service"],"created_at":"2018-06-29T21:51:00Z","pushed_at":"2019-02-24T19:40:57Z","stargazers_count":137,"language":"Go"}],"frecuent_topics":{"go":1,"golang":1,"middleware":1,"micropayments":1,"pay-per-call":1}}