{"category_type":"topic","category_name":"wit","repos_data":[{"full_name":"RasaHQ/rasa","description":"💬   Open source machine learning framework to automate text- and voice-based conversations: NLU, dialogue management, connect to Slack, Facebook, and more - Create chatbots and voice assistants","topics":["nlp","machine-learning","machine-learning-library","bot","bots","botkit","rasa","wit","nlu","conversational-bots"],"created_at":"2016-10-14T12:27:49Z","pushed_at":"2024-01-12T13:52:41Z","stargazers_count":17446,"language":"Python"},{"full_name":"wit-ai/wit-go","description":"Go client for wit.ai HTTP API","topics":["go","nlu","wit"],"created_at":"2018-08-20T07:18:40Z","pushed_at":"2022-10-10T19:23:46Z","stargazers_count":148,"language":"Go"}],"frecuent_topics":{"wit":2,"nlu":2,"nlp":1,"machine-learning":1,"machine-learning-library":1}}